sync_network_disk/__aligo.py
sync_network_disk/__config.py
sync_network_disk/__log.py
sync_network_disk/__main__.py
sync_network_disk/__proxy_aligo.py
sync_network_disk/__proxy_aligo.pyi
sync_network_disk-0.1.1.dist-info/entry_points.txt
sync_network_disk-0.1.1.dist-info/METADATA
sync_network_disk-0.1.1.dist-info/WHEEL
sync_network_disk-0.1.1.dist-info/RECORD
