Metadata-Version: 2.1
Name: sync-network-disk
Version: 0.1.1
Summary: 
Author: jawide
Author-email: 596929059@qq.com
Requires-Python: >=3.10,<4.0
Classifier: Programming Language :: Python :: 3
Classifier: Programming Language :: Python :: 3.10
Classifier: Programming Language :: Python :: 3.11
Requires-Dist: aligo (>=5.5.13,<6.0.0)
Requires-Dist: configloaders (>=0.3.2,<0.4.0)
Requires-Dist: flask (>=2.2.2,<3.0.0)
Requires-Dist: watchdog (>=2.2.1,<3.0.0)
